django_boilerplate_rest/__init__.py
django_boilerplate_rest/admin.py
django_boilerplate_rest/apps.py
django_boilerplate_rest/models.py
django_boilerplate_rest/serializers.py
django_boilerplate_rest/tests.py
django_boilerplate_rest/urls.py
django_boilerplate_rest/views.py
django_boilerplate_rest/migrations/__init__.py
django_boilerplate_rest-0.1.0.dist-info/LICENSE
django_boilerplate_rest-0.1.0.dist-info/WHEEL
django_boilerplate_rest-0.1.0.dist-info/METADATA
django_boilerplate_rest-0.1.0.dist-info/RECORD
