Metadata-Version: 2.1
Name: django_boilerplate_rest
Version: 0.1.0
Summary: Django Boilerplate REST API
Home-page: https://github.com/ravuthz/django_boilerplate/tree/rest
License: UNKNOWN
Author: Ravuthz
Author-email: ravuthz@gmail.com
Requires-Python: >=3.5
Classifier: Environment :: Web Environment
Classifier: Framework :: Django
Classifier: Framework :: Django :: 3.1
Classifier: Intended Audience :: Developers
Classifier: License :: OSI Approved :: MIT License
Classifier: Operating System :: OS Independent
Classifier: Programming Language :: Python
Classifier: Programming Language :: Python :: 3
Classifier: Programming Language :: Python :: 3.6
Classifier: Programming Language :: Python :: 3.7
Classifier: Programming Language :: Python :: 3.8
Classifier: Topic :: Internet :: WWW/HTTP
Classifier: Topic :: Internet :: WWW/HTTP :: Dynamic Content
Requires-Dist: django-environ==0.4.5
Requires-Dist: django-constance==2.7.0
Requires-Dist: dj-database-url==0.5.0
Requires-Dist: django-extensions==3.0.9
Requires-Dist: djangorestframework==3.11.1
Requires-Dist: django-rest-auth==0.9.5
Requires-Dist: django-oauth-toolkit==1.3.2
Requires-Dist: django-cors-headers==3.5.0
Requires-Dist: drf-yasg==1.17.1
